aboutcode/pipeline/CHANGELOG.md
aboutcode/pipeline/README.md
aboutcode/pipeline/RELEASE.md
aboutcode/pipeline/__init__.py
docs/Makefile
docs/application-settings.rst
docs/automation.rst
docs/built-in-pipelines.rst
docs/changelog.rst
docs/command-line-interface.rst
docs/conf.py
docs/contributing.rst
docs/custom-pipelines.rst
docs/data-models.rst
docs/distros-os-images.rst
docs/faq.rst
docs/improve-docs.rst
docs/index.rst
docs/inputs.rst
docs/installation.rst
docs/introduction.rst
docs/make.bat
docs/output-files.rst
docs/policies.rst
docs/project-configuration.rst
docs/quickstart.rst
docs/rest-api.rst
docs/scancode-config.yml
docs/scanpipe-concepts.rst
docs/scanpipe-pipes.rst
docs/tutorial_api_analyze_package_archive.rst
docs/tutorial_cli_analyze_codebase.rst
docs/tutorial_cli_analyze_docker_image.rst
docs/tutorial_cli_end_to_end_scanning_to_dejacode.rst
docs/tutorial_license_policies.rst
docs/tutorial_vulnerablecode_integration.rst
docs/tutorial_web_ui_analyze_docker_image.rst
docs/tutorial_web_ui_review_scan_results.rst
docs/tutorial_web_ui_symbol_and_string_collection.rst
docs/user-interface.rst
docs/webhooks.rst
docs/_static/theme_overrides.css
docs/images/license-clarity-scan-summary.png
docs/images/output-files-download-results.png
docs/images/output-files-projects-list.png
docs/images/tutorial-cli-end-to-end-scanning-to-dejacode-scan-all-packages.png
docs/images/tutorial-cli-end-to-end-scanning-to-dejacode-submit-scan-request.png
docs/images/tutorial-find-vulnerabilities-extra-data.png
docs/images/tutorial-find-vulnerabilities-icon-link.png
docs/images/tutorial-find-vulnerabilities-packages-link.png
docs/images/tutorial-policies-compliance-alerts-column.png
docs/images/tutorial-policies-compliance-alerts-panel.png
docs/images/tutorial-web-ui-errors-list.png
docs/images/tutorial-web-ui-packages-charts.png
docs/images/tutorial-web-ui-packages-list.png
docs/images/tutorial-web-ui-project-details.png
docs/images/tutorial-web-ui-project-form.png
scancodeio-36.1.0.dist-info/licenses/LICENSE
scancodeio-36.1.0.dist-info/licenses/NOTICE
scancodeio-36.1.0.dist-info/licenses/scan.NOTICE
scancodeio-36.1.0.dist-info/METADATA
scancodeio-36.1.0.dist-info/WHEEL
scancodeio-36.1.0.dist-info/entry_points.txt
scancodeio-36.1.0.dist-info/top_level.txt
scancodeio-36.1.0.dist-info/RECORD
