Metadata-Version: 2.4
Name: scancodeio
Version: 36.1.0
Summary: Automate software composition analysis pipelines
Author-email: "nexB Inc." <info@aboutcode.org>
License-Expression: Apache-2.0
Project-URL: Homepage, https://github.com/aboutcode-org/scancode.io
Project-URL: Documentation, https://scancodeio.readthedocs.io/
Project-URL: Repository, https://github.com/aboutcode-org/scancode.io.git
Project-URL: Issues, https://github.com/aboutcode-org/scancode.io/issues
Project-URL: Changelog, https://github.com/aboutcode-org/scancode.io/blob/main/CHANGELOG.rst
Keywords: open source,scan,license,package,dependency,copyright,filetype,author,extract,licensing,scancode,scanpipe,docker,rootfs,vm,virtual machine,pipeline,code analysis,container
Classifier: Development Status :: 5 - Production/Stable
Classifier: Intended Audience :: Developers
Classifier: Intended Audience :: Information Technology
Classifier: Intended Audience :: Legal Industry
Classifier: Programming Language :: Python
Classifier: Programming Language :: Python :: 3 :: Only
Classifier: Programming Language :: Python :: 3.10
Classifier: Programming Language :: Python :: 3.11
Classifier: Programming Language :: Python :: 3.12
Classifier: Programming Language :: Python :: 3.13
Classifier: Programming Language :: Python :: 3.14
Classifier: Topic :: Utilities
Requires-Python: >=3.10
License-File: LICENSE
License-File: NOTICE
License-File: scan.NOTICE
Requires-Dist: importlib-metadata==8.7.0
Requires-Dist: setuptools==80.9.0
Requires-Dist: Django==5.2.9
Requires-Dist: django-environ==0.12.0
Requires-Dist: django-crispy-forms==2.5
Requires-Dist: crispy-bootstrap3==2024.1
Requires-Dist: django-filter==25.2
Requires-Dist: djangorestframework==3.16.1
Requires-Dist: django-taggit==6.1.0
Requires-Dist: django-htmx==1.27.0
Requires-Dist: psycopg[binary]==3.3.1
Requires-Dist: django-probes==1.8.0
Requires-Dist: rq==2.6.1
Requires-Dist: django-rq==3.2.1
Requires-Dist: redis==7.1.0
Requires-Dist: gunicorn==23.0.0
Requires-Dist: container-inspector==33.1.0
Requires-Dist: scancode-toolkit[packages]==32.5.0
Requires-Dist: extractcode[full]==31.0.0
Requires-Dist: commoncode==32.4.2
Requires-Dist: Beautifulsoup4[chardet]==4.13.4
Requires-Dist: packageurl-python==0.17.6
Requires-Dist: fetchcode==0.8.0
Requires-Dist: fetchcode-container==1.2.3.210512; sys_platform == "linux"
Requires-Dist: elf-inspector==0.0.3
Requires-Dist: go-inspector==0.5.0
Requires-Dist: rust-inspector==0.2.1
Requires-Dist: binary-inspector==0.2.0
Requires-Dist: python-inspector==0.15.0
Requires-Dist: source-inspector==0.7.1; sys_platform != "darwin" and platform_machine != "arm64"
Requires-Dist: aboutcode-toolkit==11.1.1
Requires-Dist: XlsxWriter==3.2.9
Requires-Dist: openpyxl==3.1.5
Requires-Dist: requests==2.32.5
Requires-Dist: GitPython==3.1.45
Requires-Dist: pyinstrument==5.1.1
Requires-Dist: cyclonedx-python-lib==11.6.0
Requires-Dist: jsonschema==4.25.1
Requires-Dist: matchcode-toolkit==7.2.2
Requires-Dist: univers==31.1.0
Requires-Dist: markdown-it-py==4.0.0
Requires-Dist: bleach==6.3.0
Requires-Dist: clamd==1.0.2
Requires-Dist: aboutcode.hashid==0.2.0
Requires-Dist: aboutcode.pipeline==0.2.1
Requires-Dist: scorecode==0.0.4
Provides-Extra: dev
Requires-Dist: ruff==0.14.7; extra == "dev"
Requires-Dist: doc8==2.0.0; extra == "dev"
Requires-Dist: django-debug-toolbar==6.1.0; extra == "dev"
Requires-Dist: Sphinx==8.1.3; extra == "dev"
Requires-Dist: sphinx-rtd-theme==3.0.2; extra == "dev"
Requires-Dist: sphinx-rtd-dark-mode==1.3.0; extra == "dev"
Requires-Dist: sphinxcontrib-django==2.5; extra == "dev"
Provides-Extra: android-analysis
Requires-Dist: android_inspector==0.0.1; extra == "android-analysis"
Provides-Extra: mining
Requires-Dist: minecode_pipelines==0.1.1; extra == "mining"
Dynamic: license-file
